setup.cfg
setup.py
nyplcollections/__init__.py
nyplcollections/nyplcollections-example.py
nyplcollections/nyplcollections.py
nyplcollections.egg-info/PKG-INFO
nyplcollections.egg-info/SOURCES.txt
nyplcollections.egg-info/dependency_links.txt
nyplcollections.egg-info/requires.txt
nyplcollections.egg-info/top_level.txt