Metadata-Version: 1.1
Name: nyplcollections
Version: 1.1
Summary: new york public library image collections api
Home-page: https://github.com/nmohoric/nypl-digital-collections
Author: nick mohoric
Author-email: nick.mohoric@gmail.com
License: UNKNOWN
Download-URL: https://github.com/nmohoric/nypl-digital-collections/tarball/v1.1
Platform: UNKNOWN
